p1api/__about__.py
p1api/__init__.py
p1api/p1api.py
phase1api-0.0.2.dist-info/METADATA
phase1api-0.0.2.dist-info/WHEEL
phase1api-0.0.2.dist-info/licenses/LICENSE
phase1api-0.0.2.dist-info/RECORD
